{
  "project_info": {
    "project_number": "101172943999",
    "project_id": "local-link-63f75",
    "storage_bucket": "local-link-63f75.firebasestorage.app"
  },
  "client": [
    {
      "client_info": {
        "mobilesdk_app_id": "1:101172943999:android:dbe4cb8589b1157d8eb34a",
        "android_client_info": {
          "package_name": "com.example.local_link"
        }
      },
      "oauth_client": [],
      "api_key": [
        {
          "current_key": "AIzaSyCpkbeajrAwYbw1Z1itIOyNhEGdokbAbdY"
        }
      ],
      "services": {
        "appinvite_service": {
          "other_platform_oauth_client": []
        }
      }
    }
  ],
  "configuration_version": "1"
}